{"packages":{"darkaonline/ripcord":{"V0.1":{"name":"darkaonline/ripcord","description":"RPC client and server around PHP's xmlrpc library","keywords":["rpc","xml","xmlrpc"],"homepage":"","version":"V0.1","version_normalized":"0.1.0.0","license":["MIT"],"authors":[{"name":"Darius Matulionis","email":"darius@matulionis.lt"}],"source":{"type":"git","url":"https://github.com/DarkaOnLine/Ripcord.git","reference":"9359cf1b75ddbe34899dcd7bf14c413cbb36e64c"},"dist":{"type":"zip","url":"https://api.github.com/repos/DarkaOnLine/Ripcord/zipball/9359cf1b75ddbe34899dcd7bf14c413cbb36e64c","reference":"9359cf1b75ddbe34899dcd7bf14c413cbb36e64c","shasum":""},"type":"library","time":"2015-11-05T11:41:44+00:00","autoload":{"psr-4":{"Ripcord\\":"src/Ripcord"}},"require":{"php":">=5.4"},"uid":574735},"V0.1.1":{"name":"darkaonline/ripcord","description":"RPC client and server around PHP's xmlrpc library","keywords":["rpc","xml","xmlrpc"],"homepage":"","version":"V0.1.1","version_normalized":"0.1.1.0","license":["MIT"],"authors":[{"name":"Darius Matulionis","email":"darius@matulionis.lt"}],"source":{"type":"git","url":"https://github.com/DarkaOnLine/Ripcord.git","reference":"97b9fccf995c4cdfb76ad0c5b2d55d4d69cf2a45"},"dist":{"type":"zip","url":"https://api.github.com/repos/DarkaOnLine/Ripcord/zipball/97b9fccf995c4cdfb76ad0c5b2d55d4d69cf2a45","reference":"97b9fccf995c4cdfb76ad0c5b2d55d4d69cf2a45","shasum":""},"type":"library","time":"2015-11-05T11:48:19+00:00","autoload":{"psr-4":{"Ripcord\\":"src/Ripcord"}},"require":{"php":">=5.4"},"uid":574745},"dev-master":{"name":"darkaonline/ripcord","description":"RPC client and server around PHP's xmlrpc library","keywords":["rpc","xml","xmlrpc"],"homepage":"","version":"dev-master","version_normalized":"9999999-dev","license":["MIT"],"authors":[{"name":"Darius Matulionis","email":"darius@matulionis.lt"}],"source":{"type":"git","url":"https://github.com/DarkaOnLine/Ripcord.git","reference":"7d677fde9b4ba361bb0ed716bf92f7f620cf020f"},"dist":{"type":"zip","url":"https://api.github.com/repos/DarkaOnLine/Ripcord/zipball/7d677fde9b4ba361bb0ed716bf92f7f620cf020f","reference":"7d677fde9b4ba361bb0ed716bf92f7f620cf020f","shasum":""},"type":"library","funding":[{"url":"https://github.com/DarkaOnLine","type":"github"}],"time":"2020-04-25T16:14:30+00:00","autoload":{"psr-4":{"Ripcord\\":"src/Ripcord"}},"default-branch":true,"require":{"php":">=5.4"},"require-dev":{"friendsofphp/php-cs-fixer":"^2.14@dev"},"uid":4042462},"v0.1.2":{"name":"darkaonline/ripcord","description":"RPC client and server around PHP's xmlrpc library","keywords":["rpc","xml","xmlrpc"],"homepage":"","version":"v0.1.2","version_normalized":"0.1.2.0","license":["MIT"],"authors":[{"name":"Darius Matulionis","email":"darius@matulionis.lt"}],"source":{"type":"git","url":"https://github.com/DarkaOnLine/Ripcord.git","reference":"1b689556bb85ae02598f7ae8ee875040a340327c"},"dist":{"type":"zip","url":"https://api.github.com/repos/DarkaOnLine/Ripcord/zipball/1b689556bb85ae02598f7ae8ee875040a340327c","reference":"1b689556bb85ae02598f7ae8ee875040a340327c","shasum":""},"type":"library","time":"2016-08-16T08:34:01+00:00","autoload":{"psr-4":{"Ripcord\\":"src/Ripcord"}},"require":{"php":">=5.4"},"uid":949350},"v0.1.3":{"name":"darkaonline/ripcord","description":"RPC client and server around PHP's xmlrpc library","keywords":["rpc","xml","xmlrpc"],"homepage":"","version":"v0.1.3","version_normalized":"0.1.3.0","license":["MIT"],"authors":[{"name":"Darius Matulionis","email":"darius@matulionis.lt"}],"source":{"type":"git","url":"https://github.com/DarkaOnLine/Ripcord.git","reference":"3415d3de1f911edda28056e36a84df1b41563ff3"},"dist":{"type":"zip","url":"https://api.github.com/repos/DarkaOnLine/Ripcord/zipball/3415d3de1f911edda28056e36a84df1b41563ff3","reference":"3415d3de1f911edda28056e36a84df1b41563ff3","shasum":""},"type":"library","time":"2016-11-01T10:15:57+00:00","autoload":{"psr-4":{"Ripcord\\":"src/Ripcord"}},"require":{"php":">=5.4"},"uid":1061823},"v0.1.4":{"name":"darkaonline/ripcord","description":"RPC client and server around PHP's xmlrpc library","keywords":["rpc","xml","xmlrpc"],"homepage":"","version":"v0.1.4","version_normalized":"0.1.4.0","license":["MIT"],"authors":[{"name":"Darius Matulionis","email":"darius@matulionis.lt"}],"source":{"type":"git","url":"https://github.com/DarkaOnLine/Ripcord.git","reference":"b485483a931d68f0935933ad563e3a164e873df3"},"dist":{"type":"zip","url":"https://api.github.com/repos/DarkaOnLine/Ripcord/zipball/b485483a931d68f0935933ad563e3a164e873df3","reference":"b485483a931d68f0935933ad563e3a164e873df3","shasum":""},"type":"library","time":"2017-05-24T05:49:36+00:00","autoload":{"psr-4":{"Ripcord\\":"src/Ripcord"}},"require":{"php":">=5.4"},"uid":1409671},"v0.1.5":{"name":"darkaonline/ripcord","description":"RPC client and server around PHP's xmlrpc library","keywords":["rpc","xml","xmlrpc"],"homepage":"","version":"v0.1.5","version_normalized":"0.1.5.0","license":["MIT"],"authors":[{"name":"Darius Matulionis","email":"darius@matulionis.lt"}],"source":{"type":"git","url":"https://github.com/DarkaOnLine/Ripcord.git","reference":"30f2844742d9417d205b1f1d99ccb402bb5054df"},"dist":{"type":"zip","url":"https://api.github.com/repos/DarkaOnLine/Ripcord/zipball/30f2844742d9417d205b1f1d99ccb402bb5054df","reference":"30f2844742d9417d205b1f1d99ccb402bb5054df","shasum":""},"type":"library","time":"2018-01-10T14:02:37+00:00","autoload":{"psr-4":{"Ripcord\\":"src/Ripcord"}},"require":{"php":">=5.4"},"uid":1835147},"v0.1.6":{"name":"darkaonline/ripcord","description":"RPC client and server around PHP's xmlrpc library","keywords":["rpc","xml","xmlrpc"],"homepage":"","version":"v0.1.6","version_normalized":"0.1.6.0","license":["MIT"],"authors":[{"name":"Darius Matulionis","email":"darius@matulionis.lt"}],"source":{"type":"git","url":"https://github.com/DarkaOnLine/Ripcord.git","reference":"66eb8a68c07b74d604f6e0efdc28c9f80c2cf9d4"},"dist":{"type":"zip","url":"https://api.github.com/repos/DarkaOnLine/Ripcord/zipball/66eb8a68c07b74d604f6e0efdc28c9f80c2cf9d4","reference":"66eb8a68c07b74d604f6e0efdc28c9f80c2cf9d4","shasum":""},"type":"library","time":"2018-01-11T06:11:58+00:00","autoload":{"psr-4":{"Ripcord\\":"src/Ripcord"}},"require":{"php":">=5.4"},"uid":1836389},"v0.1.7":{"name":"darkaonline/ripcord","description":"RPC client and server around PHP's xmlrpc library","keywords":["rpc","xml","xmlrpc"],"homepage":"","version":"v0.1.7","version_normalized":"0.1.7.0","license":["MIT"],"authors":[{"name":"Darius Matulionis","email":"darius@matulionis.lt"}],"source":{"type":"git","url":"https://github.com/DarkaOnLine/Ripcord.git","reference":"e37abe596f505236c489b3f8a8e6eaa2ad7d91f7"},"dist":{"type":"zip","url":"https://api.github.com/repos/DarkaOnLine/Ripcord/zipball/e37abe596f505236c489b3f8a8e6eaa2ad7d91f7","reference":"e37abe596f505236c489b3f8a8e6eaa2ad7d91f7","shasum":""},"type":"library","time":"2019-01-02T06:13:30+00:00","autoload":{"psr-4":{"Ripcord\\":"src/Ripcord"}},"require":{"php":">=5.4"},"require-dev":{"friendsofphp/php-cs-fixer":"^2.14@dev"},"uid":2667162}}}}